odoo/addons/ddmrp_cron_actions_as_job/README.rst
odoo/addons/ddmrp_cron_actions_as_job/__init__.py
odoo/addons/ddmrp_cron_actions_as_job/__manifest__.py
odoo/addons/ddmrp_cron_actions_as_job/data/queue_job_channel_data.xml
odoo/addons/ddmrp_cron_actions_as_job/data/queue_job_function_data.xml
odoo/addons/ddmrp_cron_actions_as_job/i18n/ddmrp_cron_actions_as_job.pot
odoo/addons/ddmrp_cron_actions_as_job/i18n/es.po
odoo/addons/ddmrp_cron_actions_as_job/i18n/it.po
odoo/addons/ddmrp_cron_actions_as_job/i18n/pt_BR.po
odoo/addons/ddmrp_cron_actions_as_job/models/__init__.py
odoo/addons/ddmrp_cron_actions_as_job/models/stock_buffer.py
odoo/addons/ddmrp_cron_actions_as_job/models/stock_move.py
odoo/addons/ddmrp_cron_actions_as_job/readme/CONTRIBUTORS.rst
odoo/addons/ddmrp_cron_actions_as_job/readme/DESCRIPTION.rst
odoo/addons/ddmrp_cron_actions_as_job/static/description/icon.png
odoo/addons/ddmrp_cron_actions_as_job/static/description/index.html
odoo/addons/ddmrp_cron_actions_as_job/tests/__init__.py
odoo/addons/ddmrp_cron_actions_as_job/tests/test_cron_actions_as_job.py
odoo14_addon_ddmrp_cron_actions_as_job-14.0.1.0.1.dev8.dist-info/METADATA
odoo14_addon_ddmrp_cron_actions_as_job-14.0.1.0.1.dev8.dist-info/WHEEL
odoo14_addon_ddmrp_cron_actions_as_job-14.0.1.0.1.dev8.dist-info/top_level.txt
odoo14_addon_ddmrp_cron_actions_as_job-14.0.1.0.1.dev8.dist-info/RECORD
